pydreo/__init__.py
pydreo/client.py
pydreo/const.py
pydreo/exceptions.py
pydreo/helpers.py
pydreo_cloud-1.0.0.dist-info/licenses/LICENSE
pydreo_cloud-1.0.0.dist-info/METADATA
pydreo_cloud-1.0.0.dist-info/WHEEL
pydreo_cloud-1.0.0.dist-info/top_level.txt
pydreo_cloud-1.0.0.dist-info/RECORD
